tuxbake/__init__.py
tuxbake/__main__.py
tuxbake/argparse.py
tuxbake/build.py
tuxbake/exceptions.py
tuxbake/helper.py
tuxbake/metadata.pl
tuxbake/metadata.py
tuxbake/models.py
tuxbake/utils.py
tuxbake/metadata/hardware.ini
tuxbake/metadata/os.ini
tuxbake/metadata/resources.ini
tuxbake/metadata/tools.ini
tuxbake/metadata/uname.ini
tuxbake-1.0.0.dist-info/entry_points.txt
tuxbake-1.0.0.dist-info/LICENSE
tuxbake-1.0.0.dist-info/WHEEL
tuxbake-1.0.0.dist-info/METADATA
tuxbake-1.0.0.dist-info/RECORD
