Metadata-Version: 2.1
Name: tuxbake
Version: 1.0.0
Summary: Command line tool to build OpenEmbedded and Yocto images
Home-page: https://tuxbake.org/
Author: Vishal Bhoj
Author-email: vishal.bhoj@linaro.org
Requires-Python: >=3.6
Classifier: License :: OSI Approved :: MIT License
Requires-Dist: pyyaml
Requires-Dist: retrying
Requires-Dist: tuxmake >=1.2.0
